[
  {
    "command": "add",
    "parent": "/",
    "type": "slide",
    "props": {
      "layout": "blank",
      "background": "000000"
    }
  },
  {
    "command": "add",
    "parent": "/slide[last()]",
    "type": "shape",
    "props": {
      "name": "PricingTitle",
      "text": "Pricing",
      "x": "2.2cm",
      "y": "1.0cm",
      "width": "29.47cm",
      "height": "1.8cm",
      "font": "Arial",
      "size": "36",
      "bold": "true",
      "color": "F5F5F7",
      "fill": "none"
    }
  },
  {
    "command": "add",
    "parent": "/slide[last()]",
    "type": "shape",
    "props": {
      "preset": "roundRect",
      "fill": "1C1C1E",
      "line": "3A3A3C",
      "name": "Tier1Bg",
      "x": "2.2cm",
      "y": "3.6cm",
      "width": "14.18cm",
      "height": "14.6cm"
    }
  },
  {
    "command": "add",
    "parent": "/slide[last()]",
    "type": "shape",
    "props": {
      "font": "Arial",
      "size": "24",
      "bold": "true",
      "color": "F5F5F7",
      "align": "center",
      "fill": "none",
      "name": "Tier1Name",
      "text": "Starter",
      "x": "2.55cm",
      "y": "4.4cm",
      "width": "13.48cm",
      "height": "1.31cm"
    }
  },
  {
    "command": "add",
    "parent": "/slide[last()]",
    "type": "shape",
    "props": {
      "font": "Arial",
      "size": "60",
      "bold": "true",
      "color": "F5F5F7",
      "align": "center",
      "fill": "none",
      "name": "Tier1Price",
      "text": "$0",
      "x": "2.55cm",
      "y": "6.06cm",
      "width": "13.48cm",
      "height": "2.9cm"
    }
  },
  {
    "command": "add",
    "parent": "/slide[last()]",
    "type": "shape",
    "props": {
      "font": "Arial",
      "size": "14",
      "color": "A0A6B0",
      "align": "center",
      "fill": "none",
      "name": "Tier1Period",
      "text": "",
      "x": "2.55cm",
      "y": "9.31cm",
      "width": "13.48cm",
      "height": "0.87cm"
    }
  },
  {
    "command": "add",
    "parent": "/slide[last()]",
    "type": "shape",
    "props": {
      "font": "Arial",
      "size": "16",
      "color": "A0A6B0",
      "fill": "none",
      "name": "Tier1Features",
      "text": "• Feature A",
      "x": "2.55cm",
      "y": "10.52cm",
      "width": "13.48cm",
      "height": "6.88cm"
    }
  },
  {
    "command": "add",
    "parent": "/slide[last()]",
    "type": "shape",
    "props": {
      "preset": "roundRect",
      "fill": "0B5FFF",
      "line": "none",
      "name": "Tier2Bg",
      "x": "17.48cm",
      "y": "3.6cm",
      "width": "14.18cm",
      "height": "14.6cm"
    }
  },
  {
    "command": "add",
    "parent": "/slide[last()]",
    "type": "shape",
    "props": {
      "font": "Arial",
      "size": "24",
      "bold": "true",
      "color": "FFFFFF",
      "align": "center",
      "fill": "none",
      "name": "Tier2Name",
      "text": "Pro",
      "x": "17.84cm",
      "y": "4.4cm",
      "width": "13.48cm",
      "height": "1.31cm"
    }
  },
  {
    "command": "add",
    "parent": "/slide[last()]",
    "type": "shape",
    "props": {
      "font": "Arial",
      "size": "60",
      "bold": "true",
      "color": "FFFFFF",
      "align": "center",
      "fill": "none",
      "name": "Tier2Price",
      "text": "$29",
      "x": "17.84cm",
      "y": "6.06cm",
      "width": "13.48cm",
      "height": "2.9cm"
    }
  },
  {
    "command": "add",
    "parent": "/slide[last()]",
    "type": "shape",
    "props": {
      "font": "Arial",
      "size": "14",
      "color": "FFFFFF",
      "align": "center",
      "fill": "none",
      "name": "Tier2Period",
      "text": "",
      "x": "17.84cm",
      "y": "9.31cm",
      "width": "13.48cm",
      "height": "0.87cm"
    }
  },
  {
    "command": "add",
    "parent": "/slide[last()]",
    "type": "shape",
    "props": {
      "font": "Arial",
      "size": "16",
      "color": "FFFFFF",
      "fill": "none",
      "name": "Tier2Features",
      "text": "• Everything in Starter",
      "x": "17.84cm",
      "y": "10.52cm",
      "width": "13.48cm",
      "height": "6.88cm"
    }
  },
  {
    "command": "add",
    "parent": "/slide[last()]",
    "type": "notes",
    "props": {
      "text": "Anchor on the highlighted tier."
    }
  }
]
